myvectors/__init__.py
myvectors/myvectors.py
myvectors-1.1.dist-info/LICENSE
myvectors-1.1.dist-info/METADATA
myvectors-1.1.dist-info/WHEEL
myvectors-1.1.dist-info/top_level.txt
myvectors-1.1.dist-info/RECORD
