Metadata-Version: 2.1
Name: myvectors
Version: 1.1
Summary: Exploring VECTOR Mathematics 
Home-page: https://github.com/SHREYAS1188/vector_python_package
Download-URL: https://github.com/SHREYAS1188/vector_python_package/archive/0.9.tar.gz
Author: Shreyas Potdar
Author-email: shreyasmp2001@gmail.com
License: MIT
Classifier: Intended Audience :: Developers
Classifier: Intended Audience :: End Users/Desktop
Classifier: License :: OSI Approved :: MIT License
Classifier: Programming Language :: Python :: 3
Classifier: Programming Language :: Python :: 3.4
Classifier: Programming Language :: Python :: 3.5
Classifier: Programming Language :: Python :: 3.6
Classifier: Programming Language :: Python :: 3.7
Classifier: Programming Language :: Python :: 3.8
Classifier: Programming Language :: Python :: 3.9
Classifier: Programming Language :: Python :: 3.10
Classifier: Programming Language :: Python :: 3.11
License-File: LICENSE
Requires-Dist: matplotlib
Requires-Dist: numpy
